rest_base/__init__.py
rest_base/admin.py
rest_base/apps.py
rest_base/authentication.py
rest_base/commands.py
rest_base/errors.py
rest_base/expressions.py
rest_base/fields.py
rest_base/models.py
rest_base/settings.py
rest_base/urls.py
rest_base/views.py
rest_base/channels/__init__.py
rest_base/channels/consumers.py
rest_base/channels/core.py
rest_base/channels/routing.py
rest_base/conf/__init__.py
rest_base/management/__init__.py
rest_base/management/commands/__init__.py
rest_base/management/commands/dump.py
rest_base/management/commands/load.py
rest_base/management/commands/startapp.py
rest_base/utils/__init__.py
rest_base/utils/collection.py
rest_base/utils/dotenv.py
rest_base/utils/ip.py
rest_base/utils/models.py
rest_base/utils/random.py
rest_base/utils/registry.py
rest_base/utils/token.py
rest_base/utils/worker.py
django_rest_base-0.1.8.dist-info/LICENSE
django_rest_base-0.1.8.dist-info/METADATA
django_rest_base-0.1.8.dist-info/WHEEL
django_rest_base-0.1.8.dist-info/top_level.txt
django_rest_base-0.1.8.dist-info/RECORD
