Metadata-Version: 2.1
Name: django-rest-base
Version: 0.1.8
Summary: Customized features and environment for building a Django REST framework app.
Home-page: https://github.com/devluci/django-rest-base
Author: Lucid (@devluci)
Author-email: contact@lucid.dev
License: MIT
Platform: UNKNOWN
Classifier: Development Status :: 4 - Beta
Classifier: Environment :: Web Environment
Classifier: Topic :: Internet :: WWW/HTTP
Classifier: Intended Audience :: Developers
Classifier: License :: OSI Approved :: MIT License
Classifier: Operating System :: OS Independent
Classifier: Programming Language :: Python
Classifier: Programming Language :: Python :: 3 :: Only
Classifier: Programming Language :: Python :: 3.8
Classifier: Framework :: Django
Classifier: Framework :: Django :: 3.0
Requires-Python: >=3.8
Requires-Dist: Django (==3.*)
Requires-Dist: djangorestframework (>=3.10)
Provides-Extra: channels
Requires-Dist: channels (==2.3.1) ; extra == 'channels'
Provides-Extra: jwt
Requires-Dist: PyJWT ; extra == 'jwt'
Provides-Extra: random
Requires-Dist: numpy ; extra == 'random'
Provides-Extra: sentry
Requires-Dist: sentry-sdk ; extra == 'sentry'
